salyam/__init__.py
salyam/api.py
salyam/core.py
salyam/db.py
salyam/middleware.py
salyam/response.py
Salyam-0.1.2.dist-info/METADATA
Salyam-0.1.2.dist-info/WHEEL
Salyam-0.1.2.dist-info/top_level.txt
Salyam-0.1.2.dist-info/RECORD
