Metadata-Version: 2.1
Name: Salyam
Version: 0.1.2
Summary: Salyam Python Web Framework built for learning purposes.
Author: Komilov Murodjon
Author-email: murodjon.work@gmail.com
License: MIT
Classifier: Programming Language :: Python :: 3.6
Requires-Python: >=3.6.0
Requires-Dist: Jinja2<3.0,>=2.10.3
Requires-Dist: parse>=1.12.1
Requires-Dist: requests<3.0,>=2.31.0
Requires-Dist: requests-wsgi-adapter>=0.4.1
Requires-Dist: WebOb<2.0,>=1.8.5
Requires-Dist: whitenoise<6.0,>=4.1.4
